ITR/.DS_Store
ITR/__init__.py
ITR/configs.py
ITR/data/__init__.py
ITR/data/bloomberg.py
ITR/data/cdp.py
ITR/data/csv.py
ITR/data/data_provider.py
ITR/data/excel.py
ITR/data/inmemory.py
ITR/data/iss.py
ITR/data/msci.py
ITR/data/sbti.py
ITR/data/trucost.py
ITR/data/urgentem.py
ITR/inputs/AR6_regression_model.json
ITR/inputs/SR15_regression_model.json
ITR/inputs/current-Companies-Taking-Action.xlsx
ITR/interfaces.py
ITR/portfolio_aggregation.py
ITR/portfolio_coverage_tvp.py
ITR/target_validation.py
ITR/temperature_score.py
ITR/utils.py
wwf_itr-1.5.3.dist-info/METADATA
wwf_itr-1.5.3.dist-info/WHEEL
wwf_itr-1.5.3.dist-info/licenses/LICENSE
wwf_itr-1.5.3.dist-info/RECORD
