Metadata-Version: 2.4
Name: WWF-ITR
Version: 1.5.3
Summary: This package helps companies and financial institutions to assess the temperature alignment of current climate reduction targets and commitments for investment and lending portfolios. The tool can also be used to develop targets for official validation by the SBTi.'
License: MIT
License-File: LICENSE
Keywords: Climate,ITR,SBTi,Finance,WWF
Author: wwf
Author-email: ekonomi-finans@wwf.se
Requires-Python: >=3.10,<4.0
Classifier: Intended Audience :: Developers
Classifier: Intended Audience :: Science/Research
Classifier: License :: OSI Approved :: MIT License
Classifier: Operating System :: MacOS
Classifier: Operating System :: Microsoft :: Windows
Classifier: Operating System :: Unix
Classifier: Programming Language :: Python
Classifier: Programming Language :: Python :: 3
Classifier: Programming Language :: Python :: 3.10
Classifier: Programming Language :: Python :: 3.11
Classifier: Programming Language :: Python :: 3.12
Classifier: Programming Language :: Python :: 3.13
Classifier: Programming Language :: Python :: 3.14
Classifier: Programming Language :: Python :: 3 :: Only
Classifier: Programming Language :: Python :: 3.9
Classifier: Topic :: Scientific/Engineering
Classifier: Topic :: Software Development
Requires-Dist: cleo (>=2.0.3,<3.0.0)
Requires-Dist: numpy (>=1.26,<2.1)
Requires-Dist: openpyxl (==3.1.2)
Requires-Dist: pandas (==2.2.2)
Requires-Dist: pydantic (>=2.0,<2.12)
Requires-Dist: requests (==2.32.4)
Requires-Dist: six (>=1.16.0,<2.0.0)
Requires-Dist: xlrd (==2.0.1)
Requires-Dist: xlsxwriter (>=3.0.2,<4.0.0)
Project-URL: Bug Tracker, https://github.com/WWF-Sweden/ITR-tool/issues
Project-URL: Documentation, https://wwf-sweden.github.io/ITR-tool
Project-URL: Source Code, https://github.com/WWF-Sweden/ITR-tool/issues
